rs_fsl/__init__.py
rs_fsl/_version.py
rs_fsl/rs_fsl.py
rs_fsl-0.2.dist-info/LICENSE
rs_fsl-0.2.dist-info/METADATA
rs_fsl-0.2.dist-info/WHEEL
rs_fsl-0.2.dist-info/top_level.txt
rs_fsl-0.2.dist-info/RECORD
