Metadata-Version: 2.1
Name: rs-fsl
Version: 0.2
Summary: Python interface for the Rohde-Schwarz FSL Spectrum Analyzer
Home-page: https://github.com/bleykauf/rs_fsl
Author: Bastian Leykauf
Author-email: leykauf@physik.hu-berlin.de
Maintainer: Bastian Leykauf
Maintainer-email: leykauf@physik.hu-berlin.de
License: UNKNOWN
Platform: UNKNOWN
Classifier: Programming Language :: Python :: 3
Classifier: License :: OSI Approved :: MIT License
Classifier: Operating System :: OS Independent
Classifier: Intended Audience :: Science/Research
Requires-Python: >=3.4
License-File: LICENSE
Requires-Dist: numpy
Requires-Dist: pandas
Requires-Dist: pyvisa
